glossmod_mcp/__init__.py
glossmod_mcp/server.py
glossmod_mcp-1.2.0.dist-info/licenses/LICENSE
glossmod_mcp-1.2.0.dist-info/METADATA
glossmod_mcp-1.2.0.dist-info/WHEEL
glossmod_mcp-1.2.0.dist-info/entry_points.txt
glossmod_mcp-1.2.0.dist-info/top_level.txt
glossmod_mcp-1.2.0.dist-info/RECORD
