Metadata-Version: 2.4
Name: glossmod-mcp
Version: 1.2.0
Summary: MCP 服务器 - 3DM Mod API 集成
Author-email: 小莫 <xiaomo1433675239@outlook.com>
License: MIT
Project-URL: Homepage, https://github.com/GlossMod/gloss-mod-mcp
Project-URL: Repository, https://github.com/GlossMod/gloss-mod-mcp.git
Project-URL: Documentation, https://github.com/GlossMod/gloss-mod-mcp/docs
Keywords: mcp,3dm,mod,api
Classifier: Development Status :: 4 - Beta
Classifier: Programming Language :: Python :: 3.11
Classifier: Programming Language :: Python :: 3.12
Requires-Python: >=3.11
License-File: LICENSE
Requires-Dist: mcp[cli]>=1.18.0
Requires-Dist: httpx>=0.24.0
Requires-Dist: pydantic>=2.0.0
Dynamic: license-file
